LICENSE
slippers/__init__.py
slippers/apps.py
slippers/conf.py
slippers/props.py
slippers/static/slippers/main.css
slippers/static/slippers/main.js
slippers/template.py
slippers/templates/slippers/overlay.html
slippers/templatetags/__init__.py
slippers/templatetags/slippers.py
slippers-0.6.1.dist-info/LICENSE
slippers-0.6.1.dist-info/METADATA
slippers-0.6.1.dist-info/WHEEL
slippers-0.6.1.dist-info/RECORD
