Metadata-Version: 2.1
Name: slippers
Version: 0.6.1
Summary: Build reusable components in Django without writing a single line of Python.
Home-page: https://github.com/mixxorz/slippers
License: MIT
Keywords: django,components
Author: Mitchel Cabuloy
Author-email: mixxorz@gmail.com
Requires-Python: >=3.7.0
Classifier: Development Status :: 3 - Alpha
Classifier: Environment :: Web Environment
Classifier: Framework :: Django
Classifier: Framework :: Django :: 2.2
Classifier: Framework :: Django :: 3.2
Classifier: Framework :: Django :: 4.0
Classifier: Framework :: Django :: 4.1
Classifier: Framework :: Django :: 4.2
Classifier: Intended Audience :: Developers
Classifier: License :: OSI Approved :: MIT License
Classifier: Operating System :: OS Independent
Classifier: Programming Language :: Python :: 3
Classifier: Programming Language :: Python :: 3.7
Classifier: Programming Language :: Python :: 3.8
Classifier: Programming Language :: Python :: 3.9
Classifier: Programming Language :: Python :: 3.10
Classifier: Programming Language :: Python :: 3.11
Requires-Dist: Django (>=3.2)
Requires-Dist: PyYAML (>=5.4.0)
Requires-Dist: typeguard (>=2.13.3,<3.0.0)
Requires-Dist: typing-extensions (>=4.4.0)
Project-URL: Repository, https://github.com/mixxorz/slippers
